<?xml version="1.0" encoding="utf-8"?>
<odoo>
    <record id="product_product_form_view_alpamire" model="ir.ui.view">
        <field name="name">product.product.form.view.alpamire</field>
        <field name="model">product.product</field>
        <field name="inherit_id" ref="product.product_normal_form_view"/>
        <field name="arch" type="xml">
            <xpath expr="//field[@name='barcode']" position="after">
                <field name="item"/>
                <field name="inner"/>
            </xpath>
        </field>
    </record>
</odoo>
